[
    { "title": "ค่าแรงงาน", "icon": "arm-flex", "details": ["ค่าเตรียมดิน", "ค่าปลูก รวมค่าเตรียมพันธุ์", "ค่าดูแลรักษา", "ค่าเก็บเกี่ยว รวบรวม"] },
    { "title": "ค่าวัสดุ", "icon": "package-variant", "details": ["ค่าพันธุ์", "ค่าปุ๋ย", "ค่ายาปราบศัตรูพืชและวัชพืช", "ค่าวัสดุอื่นๆ น้ำมันเชื้อเพลิง และค่าซ่อมแซมอุปกรณ์"] },
    { "title": "ค่าเช่าที่ดิน", "icon": "map-marker", "details": ["ค่าเช่าที่ดิน ค่าเช่าบ้าน"] },
    { "title": "ค่าเสื่อมอุปกรณ์", "icon": "tools", "details": ["ค่าเสื่อมอุปกรณ์"] }
]